pandamesh/__init__.py
pandamesh/common.py
pandamesh/enum_base.py
pandamesh/gmsh_enums.py
pandamesh/gmsh_fields.py
pandamesh/gmsh_geometry.py
pandamesh/gmsh_mesher.py
pandamesh/plot.py
pandamesh/preprocessor.py
pandamesh/snapping.py
pandamesh/triangle_enums.py
pandamesh/triangle_geometry.py
pandamesh/triangle_mesher.py
pandamesh/data/__init__.py
pandamesh/data/sample_data.py
pandamesh-0.2.3.dist-info/METADATA
pandamesh-0.2.3.dist-info/WHEEL
pandamesh-0.2.3.dist-info/licenses/LICENSE
pandamesh-0.2.3.dist-info/RECORD
