Metadata-Version: 2.4
Name: pandamesh
Version: 0.2.3
Summary: From geodataframe to mesh
Project-URL: Home, https://github.com/deltares/pandamesh
Project-URL: Code, https://github.com/deltares/pandamesh
Project-URL: Issues, https://github.com/deltares/pandamesh/issues
Maintainer-email: Huite Bootsma <huite.bootsma@deltares.nl>
License: MIT
License-File: LICENSE
Keywords: geopandas,mesh,unstructured grid
Classifier: Development Status :: 4 - Beta
Classifier: Intended Audience :: Science/Research
Classifier: License :: OSI Approved :: MIT License
Classifier: Operating System :: OS Independent
Classifier: Programming Language :: Python
Classifier: Programming Language :: Python :: 3
Classifier: Programming Language :: Python :: 3.9
Classifier: Programming Language :: Python :: 3.10
Classifier: Programming Language :: Python :: 3.11
Classifier: Programming Language :: Python :: 3.12
Classifier: Programming Language :: Python :: 3.13
Classifier: Programming Language :: Python :: Implementation :: CPython
Classifier: Topic :: Scientific/Engineering
Requires-Python: >=3.9
Requires-Dist: geopandas
Requires-Dist: pooch
Requires-Dist: shapely>=2.0
Requires-Dist: triangle
Provides-Extra: all
Requires-Dist: geopandas; extra == 'all'
Requires-Dist: gmsh; extra == 'all'
Requires-Dist: matplotlib; extra == 'all'
Requires-Dist: pooch; extra == 'all'
Requires-Dist: shapely>=2.0; extra == 'all'
Requires-Dist: triangle; extra == 'all'
Requires-Dist: xarray; extra == 'all'
